[
  {
    "idea_id": "idea_ai_tools_1",
    "profile_id": "ai_tools",
    "topic": "This AI tool turns a website idea into a landing page",
    "angle": "landing page layout recreation",
    "hook": "Stop coding landing page mockups from scratch today.",
    "keywords": [
      "website builder",
      "ai design",
      "landing page mockup"
    ],
    "format": "viral_curiosity_24s",
    "freshness_window_days": 14,
    "curiosity_gap": "This AI website builder generates a website draft from a prompt.",
    "visual_promise": "Watch it recreate a landing page layout instantly.",
    "payoff": "Create a landing page mockup and export clean HTML.",
    "risk_flags": [],
    "freshness_score": 65,
    "penalties": [
      "Reused 2+ keywords (website builder, ai design) from last 30 days (-20)",
      "Format fatigue: Matches recent video format 'viral_curiosity_24s' (-15)"
    ],
    "penalty_reasons": [
      "keyword_fatigue",
      "format_fatigue"
    ],
    "recent_history_matches": [
      {
        "type": "keyword_overlap",
        "history_topic": "This AI tool clones any website in one click",
        "video_id": "9dHkHFWRjII",
        "date": "2026-06-21T21:12:05.407864Z",
        "keywords": [
          "website builder",
          "ai design"
        ]
      },
      {
        "type": "keyword_overlap",
        "history_topic": "This free AI tool replaces Photoshop",
        "video_id": "mock_yt_hist_3",
        "date": "2026-06-20T18:15:00Z",
        "keywords": [
          "ai design"
        ]
      },
      {
        "type": "format_fatigue",
        "history_topic": "This AI tool clones any website in one click",
        "video_id": "9dHkHFWRjII",
        "date": "2026-06-21T21:12:05.407864Z",
        "format": "viral_curiosity_24s"
      }
    ],
    "selected": true,
    "selected_reason": "Selected as the highest scoring fresh idea (Score: 65)."
  },
  {
    "idea_id": "idea_ai_tools_2",
    "profile_id": "ai_tools",
    "topic": "3 AI tools to start a side hustle",
    "angle": "side hustle automation",
    "hook": "These 3 AI tools will build a side hustle for you in minutes.",
    "keywords": [
      "side hustle",
      "ai tools",
      "make money online"
    ],
    "format": "viral_curiosity_24s",
    "freshness_window_days": 14,
    "curiosity_gap": "But most people are using them completely wrong.",
    "visual_promise": "We show the exact screen, the generated output, and the earnings dashboard.",
    "payoff": "Use them today before they become saturated.",
    "risk_flags": [],
    "freshness_score": 0,
    "penalties": [
      "Exact topic overlap with '3 AI tools to start a side hustle' (-60)",
      "Angle recency conflict: Angle 'side hustle automation' used recently (-25)",
      "Reused 2+ keywords (side hustle, ai tools, make money online) from last 30 days (-20)",
      "Format fatigue: Matches recent video format 'viral_curiosity_24s' (-15)",
      "Money/side-hustle topic repeated recently: Matches '3 AI tools to start a side hustle' (-20)"
    ],
    "penalty_reasons": [
      "exact_topic_overlap",
      "angle_recency_conflict",
      "keyword_fatigue",
      "format_fatigue",
      "money_repetition"
    ],
    "recent_history_matches": [
      {
        "type": "exact_topic",
        "history_topic": "3 AI tools to start a side hustle",
        "video_id": "pJ0zoo0nPAY",
        "date": "2026-06-21T16:53:35.295340Z"
      },
      {
        "type": "angle_recency",
        "history_topic": "3 AI tools to start a side hustle",
        "video_id": "pJ0zoo0nPAY",
        "date": "2026-06-21T16:53:35.295340Z",
        "angle": "side hustle automation"
      },
      {
        "type": "keyword_overlap",
        "history_topic": "3 AI tools to start a side hustle",
        "video_id": "pJ0zoo0nPAY",
        "date": "2026-06-21T16:53:35.295340Z",
        "keywords": [
          "side hustle",
          "ai tools",
          "make money online"
        ]
      },
      {
        "type": "format_fatigue",
        "history_topic": "This AI tool clones any website in one click",
        "video_id": "9dHkHFWRjII",
        "date": "2026-06-21T21:12:05.407864Z",
        "format": "viral_curiosity_24s"
      },
      {
        "type": "money_repetition",
        "history_topic": "3 AI tools to start a side hustle",
        "video_id": "pJ0zoo0nPAY",
        "date": "2026-06-21T16:53:35.295340Z"
      }
    ],
    "selected": false,
    "selected_reason": null
  },
  {
    "idea_id": "idea_ai_tools_3",
    "profile_id": "ai_tools",
    "topic": "This AI website writes all your emails",
    "angle": "email productivity",
    "hook": "Stop wasting hours writing emails.",
    "keywords": [
      "write emails",
      "ai website",
      "productivity hacks"
    ],
    "format": "viral_curiosity_24s",
    "freshness_window_days": 7,
    "curiosity_gap": "This free AI website writes them exactly in your voice.",
    "visual_promise": "Showing a blank email draft auto-filling in one click.",
    "payoff": "It saves hours and sounds completely human.",
    "risk_flags": [],
    "freshness_score": 0,
    "penalties": [
      "Exact topic overlap with 'This AI website writes all your emails' (-60)",
      "Hook pattern start 'stop wasting hours' matches recent video (-25)",
      "Angle recency conflict: Angle 'email productivity' used recently (-25)",
      "Reused 2+ keywords (write emails, ai website, productivity hacks) from last 30 days (-20)",
      "Format fatigue: Matches recent video format 'viral_curiosity_24s' (-15)"
    ],
    "penalty_reasons": [
      "exact_topic_overlap",
      "hook_pattern_overlap",
      "angle_recency_conflict",
      "keyword_fatigue",
      "format_fatigue"
    ],
    "recent_history_matches": [
      {
        "type": "exact_topic",
        "history_topic": "This AI website writes all your emails",
        "video_id": "7Lu-CSmLSVs",
        "date": "2026-06-21T18:41:51.513475Z"
      },
      {
        "type": "hook_pattern",
        "history_topic": "This AI website writes all your emails",
        "video_id": "7Lu-CSmLSVs",
        "date": "2026-06-21T18:41:51.513475Z",
        "hook": "Stop wasting hours writing emails. Let this free AI website do it in seconds."
      },
      {
        "type": "angle_recency",
        "history_topic": "This AI website writes all your emails",
        "video_id": "7Lu-CSmLSVs",
        "date": "2026-06-21T18:41:51.513475Z",
        "angle": "email productivity"
      },
      {
        "type": "keyword_overlap",
        "history_topic": "This AI website writes all your emails",
        "video_id": "7Lu-CSmLSVs",
        "date": "2026-06-21T18:41:51.513475Z",
        "keywords": [
          "write emails",
          "ai website",
          "productivity hacks"
        ]
      },
      {
        "type": "format_fatigue",
        "history_topic": "This AI tool clones any website in one click",
        "video_id": "9dHkHFWRjII",
        "date": "2026-06-21T21:12:05.407864Z",
        "format": "viral_curiosity_24s"
      }
    ],
    "selected": false,
    "selected_reason": null
  },
  {
    "idea_id": "idea_ai_tools_4",
    "profile_id": "ai_tools",
    "topic": "How to create an AI voiceover using your own voice",
    "angle": "voice cloning tutorial",
    "hook": "Create an AI voiceover using your own voice with consent in seconds.",
    "keywords": [
      "personal voiceover",
      "ai voice",
      "voice cloning"
    ],
    "format": "viral_curiosity_24s",
    "freshness_window_days": 30,
    "curiosity_gap": "But you need to verify your permission first to prevent scams.",
    "visual_promise": "Record a 10 second audio clip and see it clone instantly.",
    "payoff": "Safe, consent-based voiceovers are now instant.",
    "risk_flags": [
      "voice_cloning"
    ],
    "freshness_score": 0,
    "penalties": [
      "Exact topic overlap with 'How to create an AI voiceover using your own voice' (-60)",
      "Hook pattern start 'create an ai' matches recent video (-25)",
      "Angle recency conflict: Angle 'voice cloning tutorial' used recently (-25)",
      "Reused 2+ keywords (personal voiceover, ai voice, voice cloning) from last 30 days (-20)",
      "Format fatigue: Matches recent video format 'viral_curiosity_24s' (-15)"
    ],
    "penalty_reasons": [
      "exact_topic_overlap",
      "hook_pattern_overlap",
      "angle_recency_conflict",
      "keyword_fatigue",
      "format_fatigue"
    ],
    "recent_history_matches": [
      {
        "type": "exact_topic",
        "history_topic": "How to create an AI voiceover using your own voice",
        "video_id": "4wiuATE0Gos",
        "date": "2026-06-21T19:20:01.974544Z"
      },
      {
        "type": "hook_pattern",
        "history_topic": "How to create an AI voiceover using your own voice",
        "video_id": "4wiuATE0Gos",
        "date": "2026-06-21T19:20:01.974544Z",
        "hook": "Create an AI voiceover using your own voice with consent in seconds. Here is how."
      },
      {
        "type": "angle_recency",
        "history_topic": "How to create an AI voiceover using your own voice",
        "video_id": "4wiuATE0Gos",
        "date": "2026-06-21T19:20:01.974544Z",
        "angle": "voice cloning tutorial"
      },
      {
        "type": "keyword_overlap",
        "history_topic": "How to create an AI voiceover using your own voice",
        "video_id": "4wiuATE0Gos",
        "date": "2026-06-21T19:20:01.974544Z",
        "keywords": [
          "personal voiceover",
          "ai voice",
          "voice cloning"
        ]
      },
      {
        "type": "format_fatigue",
        "history_topic": "This AI tool clones any website in one click",
        "video_id": "9dHkHFWRjII",
        "date": "2026-06-21T21:12:05.407864Z",
        "format": "viral_curiosity_24s"
      }
    ],
    "selected": false,
    "selected_reason": null
  },
  {
    "idea_id": "idea_ai_tools_5",
    "profile_id": "ai_tools",
    "topic": "3 AI extensions for Google Chrome you need today",
    "angle": "browser extension recommendations",
    "hook": "Stop using Google Chrome normally.",
    "keywords": [
      "chrome extensions",
      "google chrome",
      "ai plugins"
    ],
    "format": "viral_curiosity_24s",
    "freshness_window_days": 14,
    "curiosity_gap": "These 3 AI Chrome extensions make it twenty times smarter.",
    "visual_promise": "Quick cuts showing each extension sidebar activating in Chrome.",
    "payoff": "They are free to install and change how you browse.",
    "risk_flags": [],
    "freshness_score": 0,
    "penalties": [
      "Exact topic overlap with '3 AI extensions for Google Chrome you need today' (-60)",
      "Angle recency conflict: Angle 'browser extension recommendations' used recently (-25)",
      "Reused 2+ keywords (chrome extensions, google chrome, ai plugins) from last 30 days (-20)",
      "Format fatigue: Matches recent video format 'viral_curiosity_24s' (-15)"
    ],
    "penalty_reasons": [
      "exact_topic_overlap",
      "angle_recency_conflict",
      "keyword_fatigue",
      "format_fatigue"
    ],
    "recent_history_matches": [
      {
        "type": "exact_topic",
        "history_topic": "3 AI extensions for Google Chrome you need today",
        "video_id": "tR-hHVtTEyo",
        "date": "2026-06-21T19:59:04.857750Z"
      },
      {
        "type": "angle_recency",
        "history_topic": "3 AI extensions for Google Chrome you need today",
        "video_id": "tR-hHVtTEyo",
        "date": "2026-06-21T19:59:04.857750Z",
        "angle": "browser extension recommendations"
      },
      {
        "type": "keyword_overlap",
        "history_topic": "3 AI extensions for Google Chrome you need today",
        "video_id": "tR-hHVtTEyo",
        "date": "2026-06-21T19:59:04.857750Z",
        "keywords": [
          "chrome extensions",
          "google chrome",
          "ai plugins"
        ]
      },
      {
        "type": "format_fatigue",
        "history_topic": "This AI tool clones any website in one click",
        "video_id": "9dHkHFWRjII",
        "date": "2026-06-21T21:12:05.407864Z",
        "format": "viral_curiosity_24s"
      }
    ],
    "selected": false,
    "selected_reason": null
  },
  {
    "idea_id": "idea_ai_tools_6",
    "profile_id": "ai_tools",
    "topic": "This AI tool generates fully animated videos from text",
    "angle": "text to video animation",
    "hook": "This AI tool turns text into a full video.",
    "keywords": [
      "text to video",
      "animated videos",
      "ai video generator"
    ],
    "format": "viral_curiosity_24s",
    "freshness_window_days": 10,
    "curiosity_gap": "But the result looks almost unreal.",
    "visual_promise": "You type one sentence. It builds scenes, captions, and motion.",
    "payoff": "This could change how creators make Shorts.",
    "risk_flags": [],
    "freshness_score": 0,
    "penalties": [
      "Exact topic overlap with 'This AI tool generates fully animated videos from text' (-60)",
      "Angle recency conflict: Angle 'text to video animation' used recently (-25)",
      "Reused 2+ keywords (text to video, animated videos, ai video generator) from last 30 days (-20)",
      "Format fatigue: Matches recent video format 'viral_curiosity_24s' (-15)"
    ],
    "penalty_reasons": [
      "exact_topic_overlap",
      "angle_recency_conflict",
      "keyword_fatigue",
      "format_fatigue"
    ],
    "recent_history_matches": [
      {
        "type": "exact_topic",
        "history_topic": "This AI tool generates fully animated videos from text",
        "video_id": "fl5QPqoB9gU",
        "date": "2026-06-21T20:18:26.106965Z"
      },
      {
        "type": "angle_recency",
        "history_topic": "This AI tool generates fully animated videos from text",
        "video_id": "fl5QPqoB9gU",
        "date": "2026-06-21T20:18:26.106965Z",
        "angle": "text to video animation"
      },
      {
        "type": "keyword_overlap",
        "history_topic": "This AI tool generates fully animated videos from text",
        "video_id": "fl5QPqoB9gU",
        "date": "2026-06-21T20:18:26.106965Z",
        "keywords": [
          "text to video",
          "animated videos",
          "ai video generator"
        ]
      },
      {
        "type": "format_fatigue",
        "history_topic": "This AI tool clones any website in one click",
        "video_id": "9dHkHFWRjII",
        "date": "2026-06-21T21:12:05.407864Z",
        "format": "viral_curiosity_24s"
      }
    ],
    "selected": false,
    "selected_reason": null
  }
]